{
	"format_version": "1.12.0",
	"minecraft:geometry": [
		{
			"description": {
				"identifier": "geometry.watt_steam_engine",
				"texture_width": 64,
				"texture_height": 64,
				"visible_bounds_width": 3,
				"visible_bounds_height": 3.5,
				"visible_bounds_offset": [0, 1.25, 0]
			},
			"bones": [
				{
					"name": "base",
					"pivot": [0, 0, 0],
					"cubes": [
						{"origin": [-8, 0, -8], "size": [16, 1, 16], "uv": [0, 0]}
					]
				},
				{
					"name": "processor_holder_1",
					"pivot": [0, 0, 0],
					"cubes": [
						{"origin": [4, 1, 3], "size": [1, 10, 3], "pivot": [4.5, 6, 4.5], "rotation": [0, 0, -10], "uv": [8, 0]}
					]
				},
				{
					"name": "processor_holder_2",
					"pivot": [-1.5, 6, 4.5],
					"rotation": [0, 0, -155],
					"cubes": [
						{"origin": [-2, 1, 3], "size": [1, 10, 3], "pivot": [-1.5, 6, 4.5], "rotation": [0, 0, -10], "uv": [0, 0]}
					]
				},
				{
					"name": "processor",
					"pivot": [0, 0, 0]
				},
				{
					"name": "connections",
					"parent": "processor",
					"pivot": [0, 0, 0]
				},
				{
					"name": "animation_wheel",
					"pivot": [1.52427, 11.05038, 4.61174],
					"cubes": [
						{"origin": [0, 6, 0], "size": [3, 6, 1], "pivot": [0.5, 6.5, 0.5], "rotation": [35, 0, 0], "uv": [32, 33]},
						{"origin": [0, 4.81285, 10.03589], "size": [3, 6, 1], "pivot": [1.5, 7.81285, 10.53589], "rotation": [-27.5, 0, 0], "uv": [32, 26]},
						{"origin": [0, -2.34763, 3.2017], "size": [3, 8, 1], "pivot": [1.5, 2.65237, 5.7017], "rotation": [-90, 0, 0], "uv": [32, 17]},
						{"origin": [0.35384, 10.94461, -2.0708], "size": [2, 6, 1], "pivot": [1.35384, 13.94461, -1.5708], "rotation": [31.9869, -0.51791, -177.67791], "uv": [6, 37]},
						{"origin": [-8.03194, 14.22297, 1.05688], "size": [2, 5, 1], "pivot": [-2.53194, 17.22297, 1.55688], "rotation": [80.24083, 1.0079, 178.91954], "uv": [18, 37]},
						{"origin": [-0.45406, 13.54597, 6.6265], "size": [2, 6, 1], "pivot": [1.04594, 16.54597, 7.1265], "rotation": [118.399, -2.69745, -176.32168], "uv": [0, 37]},
						{"origin": [0.59836, 11.1275, 11.99638], "size": [2, 5, 1], "pivot": [1.59836, 14.1275, 11.49638], "rotation": [155.899, -2.69745, -176.32168], "uv": [12, 37]},
						{"origin": [1, 9.75, 3], "size": [1, 7, 3], "pivot": [1.5, 13.5, 4.5], "rotation": [0, -90, 0], "uv": [24, 27]},
						{"origin": [1, 10, 3], "size": [1, 7, 3], "pivot": [1.5, 10.5, 4.5], "rotation": [90, -50, -90], "uv": [16, 27]},
						{"origin": [1, 10, 3], "size": [1, 7, 3], "pivot": [1.5, 10.5, 4.5], "rotation": [90, 0, -90], "uv": [8, 27]},
						{"origin": [1, 10, 3], "size": [1, 7, 3], "pivot": [1.5, 10.5, 4.5], "rotation": [90, 52.5, -90], "uv": [0, 27]},
						{"origin": [1, 10, 3], "size": [1, 7, 3], "pivot": [1.5, 10.5, 4.5], "rotation": [-90.00003, 87.5, 89.99997], "uv": [24, 17]},
						{"origin": [1, 10, 3], "size": [1, 7, 3], "pivot": [1.5, 10.5, 4.5], "rotation": [-90, 50, 90], "uv": [16, 17]},
						{"origin": [1, 10, 3], "size": [1, 7, 3], "pivot": [1.5, 10.5, 4.5], "rotation": [-90, -45, 90], "uv": [0, 17]},
						{"origin": [1, 10, 3], "size": [1, 7, 3], "pivot": [1.5, 10.5, 4.5], "rotation": [-90, -2.5, 90], "uv": [8, 17]}
					]
				}
			]
		}
	]
}